shopline_sdk/__init__.py
shopline_sdk/client.py
shopline_sdk/exceptions.py
shopline_sdk/helper.py
shopline_sdk/apis/__init__.py
shopline_sdk/apis/addon_products/__init__.py
shopline_sdk/apis/addon_products/bulk_update_addon_product_quantity_by_sku.py
shopline_sdk/apis/addon_products/create_addon_product.py
shopline_sdk/apis/addon_products/get_addon_product.py
shopline_sdk/apis/addon_products/get_addon_product_stocks.py
shopline_sdk/apis/addon_products/get_addon_products.py
shopline_sdk/apis/addon_products/search_addon_products.py
shopline_sdk/apis/addon_products/update_addon_product.py
shopline_sdk/apis/addon_products/update_addon_product_quantity.py
shopline_sdk/apis/addon_products/update_addon_product_stock.py
shopline_sdk/apis/affiliate_campaigns/__init__.py
shopline_sdk/apis/affiliate_campaigns/create_affiliate_campaign.py
shopline_sdk/apis/affiliate_campaigns/delete_affiliate_campaign.py
shopline_sdk/apis/affiliate_campaigns/export_affiliate_campaign_report_to_partner.py
shopline_sdk/apis/affiliate_campaigns/get_affiliate_campaign.py
shopline_sdk/apis/affiliate_campaigns/get_affiliate_campaign_orders.py
shopline_sdk/apis/affiliate_campaigns/get_affiliate_campaign_summary.py
shopline_sdk/apis/affiliate_campaigns/get_affiliate_campaigns.py
shopline_sdk/apis/affiliate_campaigns/get_products_sales_ranking_of_campaign.py
shopline_sdk/apis/affiliate_campaigns/update_affiliate_campaign.py
shopline_sdk/apis/agents/__init__.py
shopline_sdk/apis/agents/get_agent.py
shopline_sdk/apis/agents/get_agents.py
shopline_sdk/apis/bulk_operations/__init__.py
shopline_sdk/apis/bulk_operations/get_a_bulk_operation.py
shopline_sdk/apis/bulk_operations/get_bulk_operations.py
shopline_sdk/apis/cart_item_app_metafields/__init__.py
shopline_sdk/apis/cart_item_app_metafields/bulk_create_app_metafield.py
shopline_sdk/apis/cart_item_app_metafields/bulk_delete_app_metafield.py
shopline_sdk/apis/cart_item_app_metafields/bulk_update_app_metafield.py
shopline_sdk_python-0.2.2.dist-info/licenses/LICENSE
shopline_sdk_python-0.2.2.dist-info/METADATA
shopline_sdk_python-0.2.2.dist-info/WHEEL
shopline_sdk_python-0.2.2.dist-info/top_level.txt
shopline_sdk_python-0.2.2.dist-info/RECORD
