Metadata-Version: 2.4
Name: shopline-sdk-python
Version: 0.2.2
Summary: Shopline OpenAPI on python implement. (From https://open-api.docs.shoplineapp.com)
Author-email: HsOjo <1134031392@qq.com>
License-Expression: GPL-3.0-or-later
Project-URL: Homepage, https://github.com/hsojo/shopline-sdk-python
Project-URL: Documentation, https://open-api.docs.shoplineapp.com
Project-URL: Repository, https://github.com/hsojo/shopline-sdk-python
Project-URL: Bug Tracker, https://github.com/hsojo/shopline-sdk-python/issues
Keywords: shopline,api,sdk,ecommerce
Classifier: Development Status :: 3 - Alpha
Classifier: Intended Audience :: Developers
Classifier: Operating System :: OS Independent
Classifier: Programming Language :: Python :: 3
Classifier: Programming Language :: Python :: 3.10
Classifier: Programming Language :: Python :: 3.11
Classifier: Programming Language :: Python :: 3.12
Classifier: Topic :: Software Development :: Libraries :: Python Modules
Classifier: Topic :: Internet :: WWW/HTTP
Requires-Python: >=3.10
License-File: LICENSE
Requires-Dist: aiohttp>=3.8.0
Requires-Dist: pydantic>=2.0.0
Provides-Extra: dev
Requires-Dist: build>=1.0.0; extra == "dev"
Requires-Dist: twine>=4.0.0; extra == "dev"
Requires-Dist: pytest>=7.0.0; extra == "dev"
Requires-Dist: pytest-asyncio>=0.21.0; extra == "dev"
Dynamic: license-file
